relativize_imports.py
relativize_imports-0.0.6.dist-info/LICENSE
relativize_imports-0.0.6.dist-info/METADATA
relativize_imports-0.0.6.dist-info/WHEEL
relativize_imports-0.0.6.dist-info/entry_points.txt
relativize_imports-0.0.6.dist-info/top_level.txt
relativize_imports-0.0.6.dist-info/RECORD
