Metadata-Version: 2.1
Name: relativize-imports
Version: 0.0.6
Summary: Automatically convert python absolute imports to relative.
Home-page: https://github.com/reallyliri/relativize-imports
Author: ReallyLiri
License: MIT
Platform: UNKNOWN
Classifier: License :: OSI Approved :: MIT License
Classifier: Programming Language :: Python :: 3
Classifier: Programming Language :: Python :: 3 :: Only
Classifier: Programming Language :: Python :: Implementation :: CPython
Classifier: Programming Language :: Python :: Implementation :: PyPy
Requires-Python: >=3.7
